__init__.py
mongoday/__init__.py
mongoday/field.py
mongoday/index_store.py
mongoday/model.py
mongoday/utils/__init__.py
mongoday/utils/func.py
mongoday/utils/normalizer.py
mongoday-0.0.4.dist-info/LICENSE
mongoday-0.0.4.dist-info/METADATA
mongoday-0.0.4.dist-info/WHEEL
mongoday-0.0.4.dist-info/top_level.txt
mongoday-0.0.4.dist-info/RECORD
