Metadata-Version: 2.1
Name: mongoday
Version: 0.0.4
Summary: A simple way to create documents in MongoDB
Author-email: Abrar Arshad <abrar.arshad01@gmail.com>
Project-URL: Homepage, https://github.com/abrararshad/mongoday
Project-URL: Bug Tracker, https://github.com/abrararshad/mongoday/issues
Classifier: Programming Language :: Python :: 3
Classifier: License :: OSI Approved :: MIT License
Classifier: Operating System :: OS Independent
Requires-Python: >=3.6
License-File: LICENSE
